mxgames/2048.py
mxgames/__init__.py
mxgames/__main__.py
mxgames/ai_snake.py
mxgames/game.py
mxgames/gobang.py
mxgames/life.py
mxgames/maze.py
mxgames/mine.py
mxgames/schulte.py
mxgames/snake.py
mxgames/sudoku.py
mxgames/tetris.py
mxgames/to_hell.py
mxgames-1.7.2.dist-info/LICENSE
mxgames-1.7.2.dist-info/METADATA
mxgames-1.7.2.dist-info/WHEEL
mxgames-1.7.2.dist-info/top_level.txt
mxgames-1.7.2.dist-info/RECORD
